Execute/ALU/ALU.v
// ALUControl : ALU Operation 
// 000 -> Add
// 001 -> Subtract
// 010 -> Bitwise NOT
// 011 -> Shift left logical
// 100 -> Arithmetic shift right
// 101 -> Bitwise AND
// 110 -> Bitwise OR
// 111 -> Set Less Than


module ALU(
    input [31:0] a, b,
    input [2:0] ALUControl,
    output reg [31:0] result,
    output Zero, Overflow, Negative, Carry
);

    wire [31:0] add_result;
    wire [31:0] sub_result;
    wire add_carry_out;
    wire sub_carry_out;

    assign {add_carry_out, add_result} = a + b;            
    assign {sub_carry_out, sub_result} = a + (~b) + 1;  

    always @(*) begin
        case (ALUControl)
            3'b000: result = add_result;                      // Add
            3'b001: result = sub_result;                      // Subtract
            3'b010: result = ~a;                              // Bitwise NOT
            3'b011: result = a << b[4:0];                     // Shift left logical (limit shift to 5 bits)
            3'b100: result = $signed(a) >>> b[4:0];           // Arithmetic shift right (limit shift to 5 bits)
            3'b101: result = a & b;                           // Bitwise AND
            3'b110: result = a | b;                           // Bitwise OR
            3'b111: result = (a < b) ? 32'd1 : 32'd0;         // Set Less Than (SLT)
            default: result = 32'h00000000;                   // Default: Zero
        endcase
    end

    assign Zero = (result == 32'h00000000);               
    assign Negative = result[31];                   

    assign Overflow = ((ALUControl == 3'b000) && (a[31] == b[31]) && (result[31] != a[31])) ||  // Addition overflow
                      ((ALUControl == 3'b001) && (a[31] != b[31]) && (result[31] != a[31]));   // Subtraction overflow

    assign Carry = (ALUControl == 3'b000) ? add_carry_out :   
                   (ALUControl == 3'b001) ? ~sub_carry_out :  
                   1'b0;                                    

endmodule

Execute/ALU/ALU_tb.v
module ALU_tb();

    reg [31:0] a, b;
    reg [2:0] ALUControl;
    wire [31:0] result;
    wire Zero, Overflow, Negative, Carry;

    ALU dut(a, b,  ALUControl,result, Zero, Overflow, Negative, Carry);

initial begin
    $display("Time | ALUControl | a          | b          | Result     | Zero | Overflow | Negative | Carry");
    $display("-----------------------------------------------------------------------------------------");

    // Test Addition (Normal Case)
    a = 32'd15; b = 32'd10; ALUControl = 3'b000;
    #10;

    // Test Addition with Carry
    a = 32'hFFFFFFFF; b = 32'd1; ALUControl = 3'b000;
    #10;

    // Test Subtraction (Positive Result)
    a = 32'd50; b = 32'd30; ALUControl = 3'b001;
    #10;

    // Test Subtraction (Negative Result)
    a = 32'd20; b = 32'd50; ALUControl = 3'b001;
    #10;

    // Test Subtraction with Zero Result
    a = 32'd100; b = 32'd100; ALUControl = 3'b001;
    #10;

    // Test NOT Operation
    a = 32'h0F0F0F0F; b = 32'h00000000; ALUControl = 3'b010;
    #10;

    // Test Logical Left Shift
    a = 32'd5; b = 32'd3; ALUControl = 3'b011;
    #10;

    // Test Arithmetic Right Shift (Positive Number)
    a = 32'd64; b = 32'd2; ALUControl = 3'b100;
    #10;

    // Test Arithmetic Right Shift (Negative Number)
    a = -32'd64; b = 32'd2; ALUControl = 3'b100;
    #10;

    // Test AND Operation
    a = 32'hF0F0F0F0; b = 32'h0F0F0F0F; ALUControl = 3'b101;
    #10;

    // Test OR Operation
    a = 32'hAAAA5555; b = 32'h5555AAAA; ALUControl = 3'b110;
    #10;

    // Test Set Less Than (a < b)
    a = 32'd10; b = 32'd20; ALUControl = 3'b111;
    #10;

    // Test Set Less Than (a > b)
    a = 32'd30; b = 32'd20; ALUControl = 3'b111;
    #10;

    // Test Set Less Than (a == b)
    a = 32'd25; b = 32'd25; ALUControl = 3'b111;
    #10;

    // Edge Case: Zero Flag
    a = 32'd0; b = 32'd0; ALUControl = 3'b000;
    #10;

    // Edge Case: Large Inputs
    a = 32'h7FFFFFFF; b = 32'h7FFFFFFF; ALUControl = 3'b000; // Max positive addition
    #10;

    // Edge Case: Overflow Detection
    a = 32'h7FFFFFFF; b = 32'd1; ALUControl = 3'b000; // Positive Overflow
    #10;

    a = 32'h80000000; b = -32'd1; ALUControl = 3'b001; // Negative Overflow
    #10;

    // Edge Case: Negative Flag
    a = -32'd1; b = 32'd0; ALUControl = 3'b000;
    #10;

    $finish;
end


    initial
    begin 
        $display("ALU Testbench");
        $monitor("a=%h, b=%h, ALUControl=%h, result=%h, Zero=%b, Overflow=%b, Negative=%b, Carry=%b", a, b, ALUControl, result, Zero, Overflow, Negative, Carry);
    end

    initial
    begin
        $dumpfile("ALU.vcd");
        $dumpvars(0);
    end

endmodule

Execute/ALU/ALU.vcd
$date
	Tue Jan 28 22:56:27 2025
$end
$version
	Icarus Verilog
$end
$timescale
	1s
$end
$scope module ALU_tb $end
$var wire 32 ! result [31:0] $end
$var wire 1 " Zero $end
$var wire 1 # Overflow $end
$var wire 1 $ Negative $end
$var wire 1 % Carry $end
$var reg 3 & ALUControl [2:0] $end
$var reg 32 ' a [31:0] $end
$var reg 32 ( b [31:0] $end
$scope module dut $end
$var wire 3 ) ALUControl [2:0] $end
$var wire 1 # Overflow $end
$var wire 32 * a [31:0] $end
$var wire 32 + b [31:0] $end
$var wire 32 , sub_result [31:0] $end
$var wire 1 - sub_carry_out $end
$var wire 32 . add_result [31:0] $end
$var wire 1 / add_carry_out $end
$var wire 1 " Zero $end
$var wire 1 $ Negative $end
$var wire 1 % Carry $end
$var reg 32 0 result [31:0] $end
$upscope $end
$upscope $end
$enddefinitions $end
$comment Show the parameter values. $end
$dumpall
$end
#0
$dumpvars
b11001 0
0/
b11001 .
0-
b101 ,
b1010 +
b1111 *
b0 )
b1010 (
b1111 '
b0 &
0%
0$
0#
0"
b11001 !
$end
#10
0#
1%
1"
b0 !
b0 0
b0 .
1/
b11111111111111111111111111111110 ,
b1 (
b1 +
b11111111111111111111111111111111 '
b11111111111111111111111111111111 *
#20
0"
b10100 !
b10100 0
b1010000 .
0/
b10100 ,
b1 &
b1 )
b11110 (
b11110 +
b110010 '
b110010 *
#30
0%
1$
b11111111111111111111111111100010 !
b11111111111111111111111111100010 0
b1000110 .
b11111111111111111111111111100010 ,
1-
b110010 (
b110010 +
b10100 '
b10100 *
#40
1%
1"
0$
b0 !
b0 0
b11001000 .
b0 ,
0-
b1100100 (
b1100100 +
b1100100 '
b1100100 *
#50
0%
1$
0"
b11110000111100001111000011110000 !
b11110000111100001111000011110000 0
b1111000011110000111100001111 .
b1111000011110000111100001111 ,
b10 &
b10 )
b0 (
b0 +
b1111000011110000111100001111 '
b1111000011110000111100001111 *
#60
0$
b101000 !
b101000 0
b1000 .
b10 ,
b11 &
b11 )
b11 (
b11 +
b101 '
b101 *
#70
b10000 !
b10000 0
b1000010 .
b111110 ,
b100 &
b100 )
b10 (
b10 +
b1000000 '
b1000000 *
#80
1$
b11111111111111111111111111110000 !
b11111111111111111111111111110000 0
b11111111111111111111111111000010 .
b11111111111111111111111110111110 ,
b11111111111111111111111111000000 '
b11111111111111111111111111000000 *
#90
0$
1"
b0 !
b0 0
b11111111111111111111111111111111 .
b11100001111000011110000111100001 ,
b101 &
b101 )
b1111000011110000111100001111 (
b1111000011110000111100001111 +
b11110000111100001111000011110000 '
b11110000111100001111000011110000 *
#100
1$
0"
b11111111111111111111111111111111 !
b11111111111111111111111111111111 0
b1010101010101001010101010101011 ,
b110 &
b110 )
b1010101010101011010101010101010 (
b1010101010101011010101010101010 +
b10101010101010100101010101010101 '
b10101010101010100101010101010101 *
#110
0$
b1 !
b1 0
b11110 .
b11111111111111111111111111110110 ,
1-
b111 &
b111 )
b10100 (
b10100 +
b1010 '
b1010 *
#120
1"
b0 !
b0 0
b110010 .
b1010 ,
0-
b11110 '
b11110 *
#130
b0 ,
b11001 (
b11001 +
b11001 '
b11001 *
#140
b0 .
b0 ,
0-
b0 &
b0 )
b0 (
b0 +
b0 '
b0 *
#150
1#
1$
0"
b11111111111111111111111111111110 !
b11111111111111111111111111111110 0
b11111111111111111111111111111110 .
b0 ,
b1111111111111111111111111111111 (
b1111111111111111111111111111111 +
b1111111111111111111111111111111 '
b1111111111111111111111111111111 *
#160
b1111111111111111111111111111110 ,
b10000000000000000000000000000000 !
b10000000000000000000000000000000 0
b10000000000000000000000000000000 .
b1 (
b1 +
#170
0#
1-
1$
0%
1/
b10000000000000000000000000000001 !
b10000000000000000000000000000001 0
b1111111111111111111111111111111 .
b10000000000000000000000000000001 ,
b1 &
b1 )
b11111111111111111111111111111111 (
b11111111111111111111111111111111 +
b10000000000000000000000000000000 '
b10000000000000000000000000000000 *
#180
0/
b11111111111111111111111111111111 !
b11111111111111111111111111111111 0
b11111111111111111111111111111111 .
b11111111111111111111111111111111 ,
0-
b0 &
b0 )
b0 (
b0 +
b11111111111111111111111111111111 '
b11111111111111111111111111111111 *
