InstructionFetch/Counter.v
module Counter(clk, rst, count, count_next);
    input clk, rst;
    input [31:0] count_next;
    output reg [31:0] count;

    always@(posedge clk)
    begin
        if(!rst)
            count <= 32'h00000000;
        else
            count <= count_next;
    end

endmodule

InstructionFetch/Counter/Counter_tb.v
module Counter_tb();
    reg clk, rst;
    reg [31:0] count_next;
    wire [31:0] count;

    Counter uut(
        .clk(clk),
        .rst(rst),
        .count_next(count_next),
        .count(count)
    );

    initial
    begin
        clk = 1'b0;
        forever
        begin
            #5;
            clk = ~clk;
        end
    end

    always begin
        rst = 1'b1;
        count_next = 32'h00000000;
        #10;
        count_next = 32'h00023001;
        #10;
        count_next = 32'h00646000;
        #10;
        rst = 1'b0;
        #10;
        $finish;
    end

        initial
    begin
        $dumpfile("Counter.vcd");
        $dumpvars(0);
    end

endmodule

InstructionFetch/Counter/Counter.vcd
$date
	Sun Jan 26 22:34:15 2025
$end
$version
	Icarus Verilog
$end
$timescale
	1s
$end
$scope module Counter_tb $end
$var wire 32 ! count [31:0] $end
$var reg 1 " clk $end
$var reg 32 # count_next [31:0] $end
$var reg 1 $ rst $end
$scope module uut $end
$var wire 1 " clk $end
$var wire 32 % count_next [31:0] $end
$var wire 1 $ rst $end
$var reg 32 & count [31:0] $end
$upscope $end
$upscope $end
$enddefinitions $end
$comment Show the parameter values. $end
$dumpall
$end
#0
$dumpvars
bx &
b0 %
1$
b0 #
0"
bx !
$end
#5
b0 !
b0 &
1"
#10
0"
b100011000000000001 #
b100011000000000001 %
#15
b100011000000000001 !
b100011000000000001 &
1"
#20
0"
b11001000110000000000000 #
b11001000110000000000000 %
#25
b11001000110000000000000 !
b11001000110000000000000 &
1"
#30
0"
0$
#35
b0 !
b0 &
1"
