Decode/ControlUnit/ALUDecoder.v
module ALUDecoder(ALUOp, funct3, funct7, op, ALUControl);

    input [1:0] ALUOp;
    input [2:0] funct3;
    input [6:0] funct7, op;
    output [2:0] ALUControl;

    assign ALUControl = (ALUOp == 2'b00) ? 3'b000 :
                        (ALUOp == 2'b01) ? 3'b001 :
                        ((ALUOp == 2'b10) & (funct3 == 3'b000) & ({op[5],funct7[5]} == 2'b11)) ? 3'b001 : 
                        ((ALUOp == 2'b10) & (funct3 == 3'b000) & ({op[5],funct7[5]} != 2'b11)) ? 3'b000 : 
                        ((ALUOp == 2'b10) & (funct3 == 3'b010)) ? 3'b101 : 
                        ((ALUOp == 2'b10) & (funct3 == 3'b110)) ? 3'b011 : 
                        ((ALUOp == 2'b10) & (funct3 == 3'b111)) ? 3'b010 : 
                                                                  3'b000 ;
endmodule

Decode/MainDecoder.v
module MainDecoder(Op,RegWrite,ImmSrc,ALUSrc,MemWrite,ResultSrc,Branch,ALUOp);
    input [6:0] Op;
    output RegWrite, ALUSrc, MemWrite, ResultSrc, Branch;
    output [1:0] ImmSrc, ALUOp;

    assign RegWrite = (Op == 7'b0000011 | Op == 7'b0110011 | Op == 7'b0010011 ) ? 1'b1 :
                                                              1'b0 ;
    assign ImmSrc = (Op == 7'b0100011) ? 2'b01 : 
                    (Op == 7'b1100011) ? 2'b10 :    
                                         2'b00 ;
    assign ALUSrc = (Op == 7'b0000011 | Op == 7'b0100011 | Op == 7'b0010011) ? 1'b1 :
                                                            1'b0 ;
    assign MemWrite = (Op == 7'b0100011) ? 1'b1 :
                                           1'b0 ;
    assign ResultSrc = (Op == 7'b0000011) ? 1'b1 :
                                            1'b0 ;
    assign Branch = (Op == 7'b1100011) ? 1'b1 :
                                         1'b0 ;
    assign ALUOp = (Op == 7'b0110011) ? 2'b10 :
                   (Op == 7'b1100011) ? 2'b01 :
                                        2'b00 ;

endmodule

Decode/ControlUnit/ControlUnit.v
`include "ALUDecoder.v"
`include "MainDecoder.v"

module ControlUnit(Op, RegWrite, ImmSrc, ALUSrc, MemWrite, ResultSrc, Branch, funct3, funct7, ALUControl);

    input [6:0] Op, funct7;
    input [2:0] funct3;
    output RegWrite, ALUSrc, MemWrite, ResultSrc, Branch;
    output [1:0] ImmSrc;
    output [2:0] ALUControl;

    wire [1:0] ALUOp;

    MainDecoder MainDecoder(
                .Op(Op),
                .RegWrite(RegWrite),
                .ImmSrc(ImmSrc),
                .MemWrite(MemWrite),
                .ResultSrc(ResultSrc),
                .Branch(Branch),
                .ALUSrc(ALUSrc),
                .ALUOp(ALUOp)
    );

    ALUDecoder ALUDecoder(
                            .ALUOp(ALUOp),
                            .funct3(funct3),
                            .funct7(funct7),
                            .op(Op),
                            .ALUControl(ALUControl)
    );


endmodule

Decode/ControlUnit/ControlUnit_tb.v
module ControlUnit_tb();

    reg [6:0] Op, funct7;
    reg [2:0] funct3;
    wire RegWrite, ALUSrc,MemWrite,ResultSrc,Branch;
    wire [1:0] ImmSrc;
    wire [2:0] ALUControl;

    ControlUnit dut(Op,RegWrite,ImmSrc,ALUSrc,MemWrite,ResultSrc,Branch,funct3,funct7,ALUControl);

    initial
    begin
        Op = 7'b0000011;
        funct3 = 3'b000;
        funct7 = 7'b0000000;
        #10;
        Op = 7'b0110011;
        #10
        Op = 7'b0010011;
        #10;
        Op = 7'b0100011;
        #10;
        Op = 7'b1100011;
        #10;
        Op = 7'b0000011;
        #10;
        Op = 7'b0100011;
        #10;
        Op = 7'b0010011;
        #10;
        Op = 7'b0100011;
        #10;
        Op = 7'b0000011;
        #10;
        Op = 7'b1100011;
        #10;
        Op = 7'b0110011;
        #10;
        Op = 7'b1100011;
        #50;
        Op = 7'b0000000;
        #10;
        Op = 7'b1100011;
        #10;
        Op = 7'b0110011;
        funct3 = 3'b000;
        {Op[5],funct7[5]} = 2'b11;
        #10;
        Op = 7'b0110011;
        funct3 = 3'b000;
        {Op[5],funct7[5]} = 2'b01;
        #10;
        Op = 7'b0110011;
        funct3 = 3'b010;
        #10;
        Op = 7'b0110011;
        funct3 = 3'b110;
        #10;
        Op = 7'b0110011;
        funct3 = 3'b111;   
        #10;
        Op = 7'b0110011;
        #50;
        $finish;

    end

    initial
    begin
        $dumpfile("ControlUnit.vcd");
        $dumpvars(0);
    end

endmodule

Decode/ControlUnit/ControlUnit.vcd
$date
	Mon Jan 27 08:48:47 2025
$end
$version
	Icarus Verilog
$end
$timescale
	1s
$end
$scope module ControlUnit_tb $end
$var wire 1 ! ResultSrc $end
$var wire 1 " RegWrite $end
$var wire 1 # MemWrite $end
$var wire 2 $ ImmSrc [1:0] $end
$var wire 1 % Branch $end
$var wire 1 & ALUSrc $end
$var wire 3 ' ALUControl [2:0] $end
$var reg 7 ( Op [6:0] $end
$var reg 3 ) funct3 [2:0] $end
$var reg 7 * funct7 [6:0] $end
$scope module dut $end
$var wire 7 + Op [6:0] $end
$var wire 3 , funct3 [2:0] $end
$var wire 7 - funct7 [6:0] $end
$var wire 1 ! ResultSrc $end
$var wire 1 " RegWrite $end
$var wire 1 # MemWrite $end
$var wire 2 . ImmSrc [1:0] $end
$var wire 1 % Branch $end
$var wire 1 & ALUSrc $end
$var wire 2 / ALUOp [1:0] $end
$var wire 3 0 ALUControl [2:0] $end
$scope module ALUDecoder $end
$var wire 3 1 funct3 [2:0] $end
$var wire 7 2 funct7 [6:0] $end
$var wire 7 3 op [6:0] $end
$var wire 2 4 ALUOp [1:0] $end
$var wire 3 5 ALUControl [2:0] $end
$upscope $end
$scope module MainDecoder $end
$var wire 7 6 Op [6:0] $end
$var wire 1 ! ResultSrc $end
$var wire 1 " RegWrite $end
$var wire 1 # MemWrite $end
$var wire 2 7 ImmSrc [1:0] $end
$var wire 1 % Branch $end
$var wire 1 & ALUSrc $end
$var wire 2 8 ALUOp [1:0] $end
$upscope $end
$upscope $end
$upscope $end
$enddefinitions $end
$comment Show the parameter values. $end
$dumpall
$end
#0
$dumpvars
b0 8
b0 7
b11 6
b0 5
b0 4
b11 3
b0 2
b0 1
b0 0
b0 /
b0 .
b0 -
b0 ,
b11 +
b0 *
b0 )
b11 (
b0 '
1&
0%
b0 $
0#
1"
1!
$end
#10
0&
0!
b10 /
b10 4
b10 8
b110011 (
b110011 +
b110011 3
b110011 6
#20
1&
b0 /
b0 4
b0 8
b10011 (
b10011 +
b10011 3
b10011 6
#30
0"
1&
b1 $
b1 .
b1 7
1#
b100011 (
b100011 +
b100011 3
b100011 6
#40
b1 '
b1 0
b1 5
0&
b1 /
b1 4
b1 8
b10 $
b10 .
b10 7
0#
1%
b1100011 (
b1100011 +
b1100011 3
b1100011 6
#50
1"
1&
b0 '
b0 0
b0 5
b0 $
b0 .
b0 7
b0 /
b0 4
b0 8
1!
0%
b11 (
b11 +
b11 3
b11 6
#60
0"
b1 $
b1 .
b1 7
1#
0!
b100011 (
b100011 +
b100011 3
b100011 6
#70
1"
b0 $
b0 .
b0 7
0#
b10011 (
b10011 +
b10011 3
b10011 6
#80
0"
1&
b1 $
b1 .
b1 7
1#
b100011 (
b100011 +
b100011 3
b100011 6
#90
1"
b0 $
b0 .
b0 7
0#
1!
b11 (
b11 +
b11 3
b11 6
#100
b1 '
b1 0
b1 5
0"
0&
b10 $
b10 .
b10 7
b1 /
b1 4
b1 8
0!
1%
b1100011 (
b1100011 +
b1100011 3
b1100011 6
#110
1"
b0 '
b0 0
b0 5
b0 $
b0 .
b0 7
0%
b10 /
b10 4
b10 8
b110011 (
b110011 +
b110011 3
b110011 6
#120
0"
b1 '
b1 0
b1 5
b10 $
b10 .
b10 7
1%
b1 /
b1 4
b1 8
b1100011 (
b1100011 +
b1100011 3
b1100011 6
#170
b0 '
b0 0
b0 5
b0 $
b0 .
b0 7
b0 /
b0 4
b0 8
0%
b0 (
b0 +
b0 3
b0 6
#180
b1 '
b1 0
b1 5
b10 $
b10 .
b10 7
b1 /
b1 4
b1 8
1%
b1100011 (
b1100011 +
b1100011 3
b1100011 6
#190
1"
b1 '
b1 0
b1 5
b0 $
b0 .
b0 7
0%
b10 /
b10 4
b10 8
b100000 *
b100000 -
b100000 2
b110011 (
b110011 +
b110011 3
b110011 6
#200
1&
b0 '
b0 0
b0 5
b0 /
b0 4
b0 8
b10011 (
b10011 +
b10011 3
b10011 6
#210
b101 '
b101 0
b101 5
1"
0&
b10 /
b10 4
b10 8
b10 )
b10 ,
b10 1
b110011 (
b110011 +
b110011 3
b110011 6
#220
b11 '
b11 0
b11 5
b110 )
b110 ,
b110 1
#230
b10 '
b10 0
b10 5
b111 )
b111 ,
b111 1
